mytoolbox/__init__.py
mytoolbox/cli.py
mytoolbox-0.0.1.dist-info/entry_points.txt
mytoolbox-0.0.1.dist-info/LICENSE
mytoolbox-0.0.1.dist-info/WHEEL
mytoolbox-0.0.1.dist-info/METADATA
mytoolbox-0.0.1.dist-info/RECORD
