Metadata-Version: 2.1
Name: mytoolbox
Version: 0.0.1
Summary: Top-level package for mytoolbox.
Author-email: Willie Lima <williecadete@gmail.com>
Classifier: License :: OSI Approved :: MIT License
Requires-Dist: typer==0.9.0
Project-URL: Home, https://github.com/willie-cadete/mytoolbox
